mcp_show2user/__init__.py
mcp_show2user/__main__.py
mcp_show2user/server.py
mcp_show2user/pyarmor_runtime_000000/__init__.py
mcp_show2user/pyarmor_runtime_000000/darwin_universal/pyarmor_runtime.so
iflow_mcp_show2user-0.1.3.dist-info/METADATA
iflow_mcp_show2user-0.1.3.dist-info/WHEEL
iflow_mcp_show2user-0.1.3.dist-info/entry_points.txt
iflow_mcp_show2user-0.1.3.dist-info/RECORD
